README.md
setup.py
pcpca/__init__.py
pcpca/cpca.py
pcpca/pcpca.py
pcpca.egg-info/PKG-INFO
pcpca.egg-info/SOURCES.txt
pcpca.egg-info/dependency_links.txt
pcpca.egg-info/top_level.txt