Metadata-Version: 1.1
Name: pcpca
Version: 0.1
Summary: Probabilistic contrastive principal component analysis
Home-page: https://github.com/andrewcharlesjones/pcpca
Author: Andy Jones
Author-email: ajones788@gmail.com
License: UNKNOWN
Download-URL: https://github.com/andrewcharlesjones/pcpca/archive/v_01.tar.gz
Platform: UNKNOWN
